setup.py
fhir_to_sdo/__init__.py
fhir_to_sdo/fhir_structured_definition.py
fhir_to_sdo/sdo_template.py
fhir_to_sdo/w5_metadata.py
fhir_to_sdo.egg-info/PKG-INFO
fhir_to_sdo.egg-info/SOURCES.txt
fhir_to_sdo.egg-info/dependency_links.txt
fhir_to_sdo.egg-info/requires.txt
fhir_to_sdo.egg-info/top_level.txt
scripts/fhirtosdo