Metadata-Version: 1.1
Name: fhir-to-sdo
Version: 0.2.0
Summary: HL7 FHIR to schema.org conversion utility
Home-page: http://github.com/crDDI/fhir_to_sdo
Author: Harold Solbrig
Author-email: solbrig.harold@mayo.edu
License: Apache License 2.0
Platform: UNKNOWN
Classifier: Topic :: Software Development :: Libraries
Classifier: Programming Language :: Python :: 3
Classifier: Programming Language :: Python :: 3 :: Only
